{
  "Videos": [
    {
      "title": "How to be software engineer @ Google",
      "uploader": "Algoexport",
      "job":"Software Designer",
      "views": 45
    },
    {
      "title": "Get stuck?",
      "uploader": "Girlboy",
      "job":"Hardware seller",
      "views": 3544
    },
    {
      "title": "Doesn't makes any sense",
      "uploader": "Data Junk",
      "job":"Data Scientist",
      "views": 23211
    },
    {
      "title": "FAANG job pay for my debt",
      "uploader": "Doctor986",
      "job":"QA",
      "views": 5632333
    }
  ]
}